iverilog/FA/HA.v
module HA(output rip, output c, input a, input b);
    assign
        rip = a && b;

    assign
        c = a ^ b;
endmodule

iverilog/FA/FA.v
module FA(output cout, output s, input a, input b, input cin);
    wire s0, c0, c1;
    HA ha1(c0,s0,a,b);
    HA ha2(c1,s,s0,cin);
    assign
        cout = c0 || c1;
endmodule

iverilog/FA/FA_main.v
module test;
    reg  a;
    reg  b;
    reg ripin;
    wire ripout;
    wire c;

    integer i;

    FA adder(ripout, c, a, b, ripin);

    initial
        begin
            a = 0;
            b = 0;
            ripin = 0;

            $dumpfile("test_FA_main.vcd");
            $dumpvars;

            for(i=0; i<8; i=i+1)
                begin
                    #2 {a, b, ripin} = i;
                    #1 $display("%b %b %b => risultato: %b, riporto %b", a, b, ripin, c, ripout);
                end
            $finish;
        end
endmodule

iverilog/FA/test_FA_main.vcd
$date
	Wed Oct 23 01:04:42 2024
$end
$version
	Icarus Verilog
$end
$timescale
	1s
$end
$scope module test $end
$var wire 1 ! ripout $end
$var wire 1 " c $end
$var reg 1 # a $end
$var reg 1 $ b $end
$var reg 1 % ripin $end
$var integer 32 & i [31:0] $end
$scope module adder $end
$var wire 1 # a $end
$var wire 1 $ b $end
$var wire 1 % cin $end
$var wire 1 ! cout $end
$var wire 1 ' s0 $end
$var wire 1 " s $end
$var wire 1 ( c1 $end
$var wire 1 ) c0 $end
$scope module ha1 $end
$var wire 1 # a $end
$var wire 1 $ b $end
$var wire 1 ' c $end
$var wire 1 ) rip $end
$upscope $end
$scope module ha2 $end
$var wire 1 ' a $end
$var wire 1 % b $end
$var wire 1 " c $end
$var wire 1 ( rip $end
$upscope $end
$upscope $end
$upscope $end
$enddefinitions $end
#0
$dumpvars
0)
0(
0'
b0 &
0%
0$
0#
0"
0!
$end
#3
b1 &
#5
1"
1%
#6
b10 &
#8
1'
1"
1$
0%
#9
b11 &
#11
1!
1(
0"
1%
#12
b100 &
#14
0!
0(
1"
1#
0$
0%
#15
b101 &
#17
1!
1(
0"
1%
#18
b110 &
#20
1)
0'
0(
0"
1$
0%
#21
b111 &
#23
1"
1%
#24
b1000 &
