iverilog/XOR/XOR.v
module XOR(output c, input a, input b);
    assign
        c = (!a && b) || (a && !b);
endmodule

iverilog/XOR/XOR_main.v
module test;
    reg  a;
    reg  b;
    wire c;

    integer i;

    XOR x(c, a, b);

    initial
        begin
            a = 0;
            b = 0;

            $dumpfile("test_XOR_main.vcd");
            $dumpvars;

            for(i=0; i<4; i=i+1)
                begin
                    #2 {a, b} = i;
                    #1 $display("%b %b => risultato: %b", a, b, c);
                end
            $finish;
        end
endmodule

iverilog/XOR/test_XOR_main.vcd
$date
	Wed Oct 23 01:03:53 2024
$end
$version
	Icarus Verilog
$end
$timescale
	1s
$end
$scope module test $end
$var wire 1 ! c $end
$var reg 1 " a $end
$var reg 1 # b $end
$var integer 32 $ i [31:0] $end
$scope module x $end
$var wire 1 " a $end
$var wire 1 # b $end
$var wire 1 ! c $end
$upscope $end
$upscope $end
$enddefinitions $end
#0
$dumpvars
b0 $
0#
0"
0!
$end
#3
b1 $
#5
1!
1#
#6
b10 $
#8
1"
0#
#9
b11 $
#11
0!
1#
#12
b100 $
